streamlit-p5/__init__.py
streamlit-p5/p5/index.html
streamlit-p5/p5/p5.min.js
streamlit_p5/__init__.py
streamlit_p5/p5/index.html
streamlit_p5/p5/p5.min.js
streamlit_p5-0.0.4.dist-info/METADATA
streamlit_p5-0.0.4.dist-info/WHEEL
streamlit_p5-0.0.4.dist-info/top_level.txt
streamlit_p5-0.0.4.dist-info/RECORD
