Metadata-Version: 2.1
Name: streamlit_p5
Version: 0.0.4
Summary: Bring the power of ProcessingJS (aka P5) to Streamlit. This module allows you to create Processing sketches, interact with those sketches using the mouse and keyboard, and share data between your Processing Sketch and Stremalit.
Home-page: https://streamlit-p5-examples.fly.dev/
Author: Neal Riley
Author-email: neal.riley@gmail.com
Requires-Python: >=3.7
Requires-Dist: streamlit >=0.63
Provides-Extra: devel
Requires-Dist: wheel ; extra == 'devel'
Requires-Dist: pytest ==7.4.0 ; extra == 'devel'
Requires-Dist: playwright ==1.39.0 ; extra == 'devel'
Requires-Dist: requests ==2.31.0 ; extra == 'devel'
Requires-Dist: pytest-playwright-snapshot ==1.0 ; extra == 'devel'
Requires-Dist: pytest-rerunfailures ==12.0 ; extra == 'devel'
